llm_parse/__init__.py
llm_parse/base.py
llm_parse/pdf_2_md_parser.py
llm_parse/pdf_2_text_parser.py
llm_parse/utils.py
llm_parse-0.1.5.dist-info/LICENSE
llm_parse-0.1.5.dist-info/METADATA
llm_parse-0.1.5.dist-info/WHEEL
llm_parse-0.1.5.dist-info/RECORD
