Metadata-Version: 2.3
Name: llm-parse
Version: 0.1.5
Summary: Parse data from documents optimised for downstream llm tasks.
License: MIT
Author: tanchangsheng
Author-email: tancs1994@hotmail.com
Requires-Python: >=3.10,<4.0
Classifier: License :: OSI Approved :: MIT License
Classifier: Programming Language :: Python :: 3
Classifier: Programming Language :: Python :: 3.10
Classifier: Programming Language :: Python :: 3.11
Classifier: Programming Language :: Python :: 3.12
Classifier: Programming Language :: Python :: 3.13
Requires-Dist: pymupdf (>=1.24.2,<2.0.0)
Requires-Dist: pypdf (>=4.3.1,<5.0.0)
